README.md
setup.py
edgeable/__init__.py
edgeable/database.py
edgeable/edge.py
edgeable/node.py
edgeable/threadlock.py
edgeable.egg-info/PKG-INFO
edgeable.egg-info/SOURCES.txt
edgeable.egg-info/dependency_links.txt
edgeable.egg-info/requires.txt
edgeable.egg-info/top_level.txt