Metadata-Version: 2.1
Name: edgeable
Version: 0.1.73
Summary: Easy to use, in memory, peristable graph database.
Home-page: https://github.com/leeadcock/edgeable
Author: Lee Adcock
Author-email: lee@katieandlee.com
License: MIT
Platform: UNKNOWN
Classifier: License :: OSI Approved :: MIT License
Classifier: Programming Language :: Python :: 3
Classifier: Programming Language :: Python :: 3.6
Classifier: Programming Language :: Python :: 3.7
Classifier: Programming Language :: Python :: 3.8
Classifier: Programming Language :: Python :: 3.9
